odoo/addons/website_sale_category_description/README.rst
odoo/addons/website_sale_category_description/__init__.py
odoo/addons/website_sale_category_description/__manifest__.py
odoo/addons/website_sale_category_description/i18n/es.po
odoo/addons/website_sale_category_description/i18n/website_sale_category_description.pot
odoo/addons/website_sale_category_description/models/__init__.py
odoo/addons/website_sale_category_description/models/product_public_category.py
odoo/addons/website_sale_category_description/readme/CONTRIBUTORS.rst
odoo/addons/website_sale_category_description/readme/CREDITS.rst
odoo/addons/website_sale_category_description/readme/DESCRIPTION.rst
odoo/addons/website_sale_category_description/readme/ROADMAP.rst
odoo/addons/website_sale_category_description/readme/USAGE.rst
odoo/addons/website_sale_category_description/static/description/icon.png
odoo/addons/website_sale_category_description/static/description/index.html
odoo/addons/website_sale_category_description/templates/website_sale.xml
odoo12_addon_website_sale_category_description-12.0.1.0.2.dist-info/METADATA
odoo12_addon_website_sale_category_description-12.0.1.0.2.dist-info/WHEEL
odoo12_addon_website_sale_category_description-12.0.1.0.2.dist-info/top_level.txt
odoo12_addon_website_sale_category_description-12.0.1.0.2.dist-info/RECORD
